vsml/__init__.py
vsml/func.py
vsml/tests.py
vsml.py-0.3.2.dist-info/LICENSE.txt
vsml.py-0.3.2.dist-info/METADATA
vsml.py-0.3.2.dist-info/WHEEL
vsml.py-0.3.2.dist-info/top_level.txt
vsml.py-0.3.2.dist-info/RECORD
