Metadata-Version: 2.1
Name: vsml.py
Version: 0.3.2
Summary: a very simple markup language.
Home-page: https://git.disroot.org/Galaxia/vsml.py
Author-email: satyrn@disroot.org
License: MIT
Download-URL: https://pypi.org/project/vsml.py/
Keywords: vsml,markup
Platform: UNKNOWN
Classifier: License :: OSI Approved :: MIT License
Classifier: Intended Audience :: Developers
Classifier: Programming Language :: Python :: 3 :: Only
License-File: LICENSE.txt
